pubsub_controller/__init__.py
pubsub_controller/pubsub_controller.py
pubsub_controller/settings.py
pubsub_controller/publisher/__init__.py
pubsub_controller/publisher/cli_publish.py
pubsub_controller/publisher/publish_message.py
pubsub_controller/subscriber/__init__.py
pubsub_controller/subscriber/pull/__init__.py
pubsub_controller/subscriber/pull/pull_subscriber.py
pubsub_controller/subscriber/pull/subscribe_base.py
pubsub_controller/subscriber/pull/subscribe_multi.py
pubsub_controller/subscriber/pull/exec_classes/__init__.py
pubsub_controller/subscriber/pull/exec_classes/exec_sample.py
pubsub_controller/subscriber/pull/exec_classes/gunicorn_restart.py
pubsub_controller/utils/__init__.py
pubsub_controller/utils/create_setting.py
pubsub_controller/utils/log.py
pubsub_controller-1.0.1.dist-info/DESCRIPTION.rst
pubsub_controller-1.0.1.dist-info/METADATA
pubsub_controller-1.0.1.dist-info/RECORD
pubsub_controller-1.0.1.dist-info/WHEEL
pubsub_controller-1.0.1.dist-info/entry_points.txt
pubsub_controller-1.0.1.dist-info/metadata.json
pubsub_controller-1.0.1.dist-info/top_level.txt
