Metadata-Version: 2.0
Name: pubsub-controller
Version: 1.0.1
Summary: It provides a resident process that periodically pull subscribes and publish on CLI and Python.
Home-page: https://github.com/COLORFULBOARD/pubsub_controller
Author: SENSY Inc.
Author-email: UNKNOWN
License: Apache 2.0
Platform: UNKNOWN
Requires-Dist: google-cloud-pubsub (==0.30.1)
Requires-Dist: Click (>=6.7)
Requires-Dist: six (>=1.11.0)
